{
  "id": "noble",
  "title": "Noble",
  "category": "Character Backgrounds",
  "tags": [
    "source:xphb",
    "background"
  ],
  "excerpt": "- Ability Scores: Strength, Intelligence, Charisma - Feat: skilled|Skilled - Skill Proficiencies: history|History, persuasion|Persuasion - Tool Profic...",
  "aliases": [],
  "seeAlso": [
    "skilled",
    "history",
    "persuasion",
    "fine_clothes",
    "perfume"
  ],
  "filePath": "/data/glossary/entries/backgrounds/noble.json",
  "markdown": "# Noble\n\n- **Ability Scores:** Strength, Intelligence, Charisma\n- **Feat:** [[skilled]]\n- **Skill Proficiencies:** [[history]], [[persuasion]]\n- **Tool Proficiency:** Choose one kind of Gaming Set\n- **Equipment:** Choose A or B: (A) Gaming Set (same as above), [[fine_clothes]], [[perfume]], 29 GP; or (B) 50 GP"
}