{
  "id": "costume",
  "title": "Costume",
  "category": "Equipment",
  "tags": [
    "source:xphb",
    "item"
  ],
  "excerpt": "- Type: G|XPHB - Cost: 5 gp - Weight: 4 lb. While wearing a Costume, you have advantage on any ability check you make to impersonate the person or typ...",
  "aliases": [],
  "seeAlso": [],
  "filePath": "/data/glossary/entries/equipment/costume.json",
  "markdown": "# Costume\n\n- **Type**: G|XPHB\n- **Cost**: 5 gp\n- **Weight**: 4 lb.\n\nWhile wearing a Costume, you have [[advantage]] on any ability check you make to impersonate the person or type of person it represents."
}