{
  "id": "hooded_lantern",
  "title": "Hooded Lantern",
  "category": "Equipment",
  "tags": [
    "source:xphb",
    "item"
  ],
  "excerpt": "- Type: G|XPHB - Cost: 5 gp - Weight: 2 lb. A Hooded Lantern burns Oil as fuel to cast bright_light Light in a 30-foot radius and dim_light Light for ...",
  "aliases": [],
  "seeAlso": [],
  "filePath": "/data/glossary/entries/equipment/hooded_lantern.json",
  "markdown": "# Hooded Lantern\n\n- **Type**: G|XPHB\n- **Cost**: 5 gp\n- **Weight**: 2 lb.\n\nA Hooded Lantern burns Oil as fuel to cast [[bright_light Light]] in a 30-foot radius and [[dim_light Light]] for an additional 30 feet. As a [[bonus_action Action]], you can lower the hood, reducing the light to [[dim_light Light]] in a 5-foot radius, or raise it again."
}