{
    "id":  "enhance-ability",
    "name":  "Enhance Ability",
    "aliases":  [

                ],
    "level":  2,
    "school":  "Transmutation",
    "legacy":  false,
    "classes":  [
                    "Bard",
                    "Cleric",
                    "Druid",
                    "Ranger",
                    "Sorcerer",
                    "Wizard",
                    "Artificer"
                ],
    "subClasses":  [
                       "Paladin - Oath of Glory",
                       "Paladin - Oath of Revelry",
                       "Warlock - Future You Patron"
                   ],
    "subClassesVerification":  "verified",
    "ritual":  false,
    "rarity":  "common",
    "attackType":  "",
    "castingTime":  {
                        "value":  1,
                        "unit":  "action",
                        "combatCost":  {
                                           "type":  "action",
                                           "condition":  ""
                                       },
                        "explorationCost":  {
                                                "value":  0,
                                                "unit":  "minute"
                                            }
                    },
    "range":  {
                  "type":  "touch",
                  "distance":  0
              },
    "components":  {
                       "verbal":  true,
                       "somatic":  true,
                       "material":  true,
                       "materialDescription":  "fur or a feather",
                       "isConsumed":  false,
                       "materialCost":  0
                   },
    "duration":  {
                     "type":  "timed",
                     "value":  1,
                     "unit":  "hour",
                     "concentration":  true
                 },
    "targeting":  {
                      "type":  "single",
                      "range":  0,
                      "validTargets":  [
                                           "creatures"
                                       ],
                      "lineOfSight":  true,
                      "maxTargets":  1,
                      "areaOfEffect":  {
                                           "shape":  "Sphere",
                                           "size":  0,
                                           "height":  0
                                       },
                      "filter":  {
                                     "creatureTypes":  [

                                                       ],
                                     "excludeCreatureTypes":  [

                                                              ],
                                     "sizes":  [

                                               ],
                                     "alignments":  [

                                                    ],
                                     "hasCondition":  [

                                                      ],
                                     "isNativeToPlane":  false
                                 }
                  },
    "effects":  [
                    {
                        "type":  "UTILITY",
                        "trigger":  {
                                        "type":  "immediate",
                                        "frequency":  "every_time",
                                        "consumption":  "unlimited",
                                        "attackFilter":  {
                                                             "weaponType":  "any",
                                                             "attackType":  "any"
                                                         },
                                        "movementType":  "any",
                                        "sustainCost":  {
                                                            "actionType":  "action",
                                                            "optional":  false
                                                        }
                                    },
                        "condition":  {
                                          "type":  "always",
                                          "saveType":  "Strength",
                                          "saveEffect":  "none",
                                          "targetFilter":  {
                                                               "creatureTypes":  [

                                                                                 ],
                                                               "excludeCreatureTypes":  [

                                                                                        ],
                                                               "sizes":  [

                                                                         ],
                                                               "alignments":  [

                                                                              ],
                                                               "hasCondition":  [

                                                                                ],
                                                               "isNativeToPlane":  false
                                                           },
                                          "requiresStatus":  [

                                                             ],
                                          "saveModifiers":  [

                                                            ]
                                      },
                        "utilityType":  "other",
                        "description":  "You touch a creature and bestow upon it a magical enhancement. Choose one of the following effects; the target gains that effect until the spell ends. Bear\u0027s Endurance: The target has Advantage on Constitution checks. It also gains 2d6 Temporary Hit Points, which are lost when the spell ends. Bull\u0027s Strength: The target has Advantage on Strength checks, and his or her carrying capacity doubles. Cat\u0027s Grace: The target has Advantage on Dexterity checks. It also doesn\u0027t take damage from falling 20 feet or less if it isn\u0027t Incapacitated. Eagle\u0027s Splendor: The target has Advantage on Charisma checks. Fox\u0027s Cunning: The target has Advantage on Intelligence checks. Owl\u0027s Wisdom: The target has Advantage on Wisdom checks.",
                        "scaling":  {
                                        "type":  "slot_level",
                                        "bonusPerLevel":  "",
                                        "customFormula":  ""
                                    },
                        "grantedActions":  [

                                           ],
                        "attackAugments":  [

                                           ],
                        "controlOptions":  [

                                           ],
                        "taunt":  {
                                      "disadvantageAgainstOthers":  false,
                                      "leashRangeFeet":  0,
                                      "breakConditions":  [

                                                          ]
                                  },
                        "savePenalty":  {
                                            "dice":  "",
                                            "flat":  0,
                                            "applies":  "next_save",
                                            "duration":  {
                                                             "type":  "rounds",
                                                             "value":  0
                                                         }
                                        },
                        "light":  {
                                      "brightRadius":  0,
                                      "dimRadius":  0,
                                      "attachedTo":  "caster",
                                      "color":  ""
                                  }
                    }
                ],
    "arbitrationType":  "mechanical",
    "aiContext":  {
                      "prompt":  "",
                      "playerInputRequired":  false
                  },
    "description":  "You touch a creature and choose Strength, Dexterity, Intelligence, Wisdom, or Charisma. For the duration, the target has Advantage on ability checks using the chosen ability.",
    "higherLevels":  "Using a Higher-Level Spell Slot. You can target one additional creature for each spell slot level above 2. You can choose a different ability for each target.",
    "tags":  [
                 "buff",
                 "transmutation",
                 "concentration"
             ]
}
