{
  "id": "advantage",
  "title": "Advantage",
  "category": "Rules Glossary",
  "tags": [
    "source:xphb",
    "variantrule"
  ],
  "excerpt": "If you have Advantage on a [[d20_test Test]], roll two d20s, and use the higher roll. A roll can't be affected by more than one Advantage, and Advanta...",
  "aliases": [],
  "seeAlso": [],
  "filePath": "/data/glossary/entries/rules/advantage.json",
  "markdown": "# Advantage\n\nIf you have Advantage on a [[d20_test]], roll two d20s, and use the higher roll. A roll can't be affected by more than one Advantage, and Advantage and [[disadvantage]] on the same roll cancel each other."
}
