{
  "id": "fly_speed",
  "title": "Fly Speed",
  "category": "Rules Glossary",
  "tags": [
    "source:xphb",
    "variantrule"
  ],
  "excerpt": "A Fly Speed can be used to travel through the air. While you have a Fly Speed, you can stay aloft until you land, fall, or die....",
  "aliases": [],
  "seeAlso": [],
  "filePath": "/data/glossary/entries/rules/fly_speed.json",
  "markdown": "# Fly Speed\n\nA Fly Speed can be used to travel through the air. While you have a Fly Speed, you can stay aloft until you land, fall, or die."
}