{
  "id": "ray-of-frost",
  "name": "Ray of Frost",
  "aliases": [],
  "level": 0,
  "school": "Evocation",
  "legacy": false,
  "classes": [
    "Artificer",
    "Sorcerer",
    "Wizard"
  ],
  "subClasses": [
    "Druid - Circle of the Sea"
  ],
  "ritual": false,
  "rarity": "common",
  "attackType": "",
  "castingTime": {
    "value": 1,
    "unit": "action",
    "combatCost": {
      "type": "action",
      "condition": ""
    },
    "explorationCost": {
      "value": 0,
      "unit": "minute"
    }
  },
  "range": {
    "type": "ranged",
    "distance": 60,
    "distanceUnit": "feet"
  },
  "components": {
    "verbal": true,
    "somatic": true,
    "material": false,
    "materialDescription": "",
    "materialCost": 0,
    "isConsumed": false
  },
  "duration": {
    "type": "instantaneous",
    "concentration": false,
    "value": 0,
    "unit": "round"
  },
  "targeting": {
    "type": "single",
    "range": 60,
    "rangeUnit": "feet",
    "validTargets": [
      "creatures"
    ],
    "lineOfSight": true,
    "maxTargets": 1,
    "filter": {
      "creatureTypes": [],
      "excludeCreatureTypes": [],
      "sizes": [],
      "alignments": [],
      "hasCondition": [],
      "isNativeToPlane": false,
      "willing": "not_applicable",
      "objectEligibility": {
        "wornOrCarried": "not_applicable",
        "magicalStatus": "not_applicable",
        "fixedToSurface": "not_applicable",
        "maxSize": "not_applicable",
        "maxWeightPounds": "not_applicable",
        "maxWeightScaling": "not_applicable"
      },
      "communicationPrerequisites": {
        "canHearCaster": "not_applicable",
        "canUnderstandCaster": "not_applicable",
        "canSeeCaster": "not_applicable"
      },
      "abilityThreshold": {
        "ability": "not_applicable",
        "operator": "not_applicable",
        "value": "not_applicable"
      },
      "selfRelation": "not_applicable"
    }
  },
  "effects": [
    {
      "type": "DAMAGE",
      "trigger": {
        "type": "immediate",
        "frequency": "every_time",
        "consumption": "unlimited",
        "attackFilter": {
          "weaponType": "any",
          "attackType": "any"
        },
        "movementType": "any",
        "sustainCost": {
          "actionType": "action",
          "optional": false
        }
      },
      "condition": {
        "type": "hit",
        "targetFilter": {
          "creatureTypes": [],
          "excludeCreatureTypes": [],
          "sizes": [],
          "alignments": [],
          "hasCondition": [],
          "isNativeToPlane": false,
          "willing": "not_applicable",
          "objectEligibility": {
            "wornOrCarried": "not_applicable",
            "magicalStatus": "not_applicable",
            "fixedToSurface": "not_applicable",
            "maxSize": "not_applicable",
            "maxWeightPounds": "not_applicable",
            "maxWeightScaling": "not_applicable"
          },
          "communicationPrerequisites": {
            "canHearCaster": "not_applicable",
            "canUnderstandCaster": "not_applicable",
            "canSeeCaster": "not_applicable"
          },
          "abilityThreshold": {
            "ability": "not_applicable",
            "operator": "not_applicable",
            "value": "not_applicable"
          },
          "selfRelation": "not_applicable"
        },
        "requiresStatus": [],
        "saveModifiers": [],
        "saveOutcomeOverrides": []
      },
      "damage": {
        "dice": "1d8",
        "type": "Cold"
      },
      "scaling": {
        "type": "character_level",
        "bonusPerLevel": "+1d8",
        "customFormula": "1d8 at level 1, 2d8 at level 5, 3d8 at level 11, 4d8 at level 17"
      },
      "description": "On a ranged spell hit, one target takes 1d8 Cold damage, with cantrip-tier damage scaling at character levels 5, 11, and 17.",
      "conditionalEndings": [],
      "tags": [
        "cold-damage",
        "ranged-hit",
        "cantrip-scaling"
      ]
    },
    {
      "type": "MOVEMENT",
      "trigger": {
        "type": "immediate",
        "frequency": "every_time",
        "consumption": "unlimited",
        "attackFilter": {
          "weaponType": "any",
          "attackType": "any"
        },
        "movementType": "any",
        "sustainCost": {
          "actionType": "action",
          "optional": false
        }
      },
      "condition": {
        "type": "hit",
        "targetFilter": {
          "creatureTypes": [],
          "excludeCreatureTypes": [],
          "sizes": [],
          "alignments": [],
          "hasCondition": [],
          "isNativeToPlane": false,
          "willing": "not_applicable",
          "objectEligibility": {
            "wornOrCarried": "not_applicable",
            "magicalStatus": "not_applicable",
            "fixedToSurface": "not_applicable",
            "maxSize": "not_applicable",
            "maxWeightPounds": "not_applicable",
            "maxWeightScaling": "not_applicable"
          },
          "communicationPrerequisites": {
            "canHearCaster": "not_applicable",
            "canUnderstandCaster": "not_applicable",
            "canSeeCaster": "not_applicable"
          },
          "abilityThreshold": {
            "ability": "not_applicable",
            "operator": "not_applicable",
            "value": "not_applicable"
          },
          "selfRelation": "not_applicable"
        },
        "requiresStatus": [],
        "saveModifiers": [],
        "saveOutcomeOverrides": []
      },
      "movementType": "speed_change",
      "speedChange": {
        "stat": "speed",
        "value": -10,
        "unit": "feet"
      },
      "duration": {
        "type": "rounds",
        "value": 1
      },
      "scaling": {
        "type": "slot_level",
        "bonusPerLevel": "",
        "customFormula": ""
      },
      "distance": 0,
      "forcedMovement": {
        "usesReaction": false,
        "direction": "away_from_caster",
        "maxDistance": ""
      },
      "description": "On the triggering ranged spell hit, the target's Speed is reduced by 10 feet until the start of the caster's next turn.",
      "conditionalEndings": [],
      "tags": [
        "speed-reduction",
        "movement-control",
        "hit-rider"
      ]
    }
  ],
  "arbitrationType": "mechanical",
  "aiContext": {
    "prompt": "",
    "playerInputRequired": false
  },
  "description": "A frigid beam of blue-white light streaks toward a creature within range. Make a ranged spell attack against the target. On a hit, it takes 1d8 cold damage, and its speed is reduced by 10 feet until the start of your next turn.",
  "higherLevels": "The spell's damage increases by 1d8 when you reach 5th level (2d8), 11th level (3d8), and 17th level (4d8).",
  "tags": [
    "damage",
    "cold",
    "control",
    "cantrip"
  ]
}
