{
  "id": "shadow-of-moil",
  "name": "Shadow of Moil",
  "aliases": [],
  "level": 4,
  "school": "Necromancy",
  "legacy": false,
  "classes": [
    "Warlock"
  ],
  "subClasses": [],
  "ritual": false,
  "rarity": "common",
  "attackType": "",
  "castingTime": {
    "value": 1,
    "unit": "action",
    "combatCost": {
      "type": "action",
      "condition": ""
    },
    "explorationCost": {
      "value": 0,
      "unit": "minute"
    }
  },
  "range": {
    "type": "self",
    "distance": 0
  },
  "components": {
    "verbal": true,
    "somatic": true,
    "material": true,
    "materialDescription": "an undead eyeball encased in a gem worth at least 150 gp",
    "materialCost": 150,
    "isConsumed": false
  },
  "duration": {
    "type": "timed",
    "concentration": true,
    "value": 1,
    "unit": "minute"
  },
  "targeting": {
    "type": "single",
    "range": 0,
    "validTargets": [
      "creatures"
    ],
    "lineOfSight": true,
    "maxTargets": 1,
    "filter": {
      "creatureTypes": [],
      "excludeCreatureTypes": [],
      "sizes": [],
      "alignments": [],
      "hasCondition": [],
      "isNativeToPlane": false,
      "willing": "not_applicable",
      "objectEligibility": {
        "wornOrCarried": "not_applicable",
        "magicalStatus": "not_applicable",
        "fixedToSurface": "not_applicable",
        "maxSize": "not_applicable",
        "maxWeightPounds": "not_applicable",
        "maxWeightScaling": "not_applicable"
      },
      "communicationPrerequisites": {
        "canHearCaster": "not_applicable",
        "canUnderstandCaster": "not_applicable",
        "canSeeCaster": "not_applicable"
      },
      "abilityThreshold": {
        "ability": "not_applicable",
        "operator": "not_applicable",
        "value": "not_applicable"
      },
      "selfRelation": "not_applicable"
    }
  },
  "effects": [
    {
      "type": "DAMAGE",
      "trigger": {
        "type": "on_attack_hit",
        "frequency": "every_time",
        "consumption": "unlimited",
        "attackFilter": {
          "weaponType": "any",
          "attackType": "any"
        },
        "movementType": "any",
        "sustainCost": {
          "actionType": "action",
          "optional": false
        }
      },
      "condition": {
        "type": "hit",
        "targetFilter": {
          "creatureTypes": [],
          "excludeCreatureTypes": [],
          "sizes": [],
          "alignments": [],
          "hasCondition": [],
          "isNativeToPlane": false,
          "willing": "not_applicable",
          "objectEligibility": {
            "wornOrCarried": "not_applicable",
            "magicalStatus": "not_applicable",
            "fixedToSurface": "not_applicable",
            "maxSize": "not_applicable",
            "maxWeightPounds": "not_applicable",
            "maxWeightScaling": "not_applicable"
          },
          "communicationPrerequisites": {
            "canHearCaster": "not_applicable",
            "canUnderstandCaster": "not_applicable",
            "canSeeCaster": "not_applicable"
          },
          "abilityThreshold": {
            "ability": "not_applicable",
            "operator": "not_applicable",
            "value": "not_applicable"
          },
          "selfRelation": "not_applicable"
        },
        "requiresStatus": [],
        "saveModifiers": [],
        "saveOutcomeOverrides": []
      },
      "damage": {
        "dice": "2d8",
        "type": "Necrotic"
      },
      "scaling": {
        "type": "slot_level",
        "bonusPerLevel": "",
        "customFormula": ""
      },
      "description": "Whenever a creature within 10 feet of the caster hits the caster with an attack, the shadows lash out and deal 2d8 Necrotic damage to that creature.",
      "conditionalEndings": []
    },
    {
      "type": "DEFENSIVE",
      "trigger": {
        "type": "immediate",
        "frequency": "every_time",
        "consumption": "unlimited",
        "attackFilter": {
          "weaponType": "any",
          "attackType": "any"
        },
        "movementType": "any",
        "sustainCost": {
          "actionType": "action",
          "optional": false
        }
      },
      "condition": {
        "type": "always",
        "targetFilter": {
          "creatureTypes": [],
          "excludeCreatureTypes": [],
          "sizes": [],
          "alignments": [],
          "hasCondition": [],
          "isNativeToPlane": false,
          "willing": "not_applicable",
          "objectEligibility": {
            "wornOrCarried": "not_applicable",
            "magicalStatus": "not_applicable",
            "fixedToSurface": "not_applicable",
            "maxSize": "not_applicable",
            "maxWeightPounds": "not_applicable",
            "maxWeightScaling": "not_applicable"
          },
          "communicationPrerequisites": {
            "canHearCaster": "not_applicable",
            "canUnderstandCaster": "not_applicable",
            "canSeeCaster": "not_applicable"
          },
          "abilityThreshold": {
            "ability": "not_applicable",
            "operator": "not_applicable",
            "value": "not_applicable"
          },
          "selfRelation": "not_applicable"
        },
        "requiresStatus": [],
        "saveModifiers": [],
        "saveOutcomeOverrides": []
      },
      "defenseType": "resistance",
      "damageType": [
        "Radiant"
      ],
      "duration": {
        "type": "minutes",
        "value": 1
      },
      "description": "Until the spell ends, the caster has Resistance to Radiant damage.",
      "scaling": {
        "type": "slot_level",
        "bonusPerLevel": "",
        "customFormula": ""
      },
      "conditionalEndings": []
    },
    {
      "type": "UTILITY",
      "trigger": {
        "type": "immediate",
        "frequency": "every_time",
        "consumption": "unlimited",
        "attackFilter": {
          "weaponType": "any",
          "attackType": "any"
        },
        "movementType": "any",
        "sustainCost": {
          "actionType": "action",
          "optional": false
        }
      },
      "condition": {
        "type": "always",
        "targetFilter": {
          "creatureTypes": [],
          "excludeCreatureTypes": [],
          "sizes": [],
          "alignments": [],
          "hasCondition": [],
          "isNativeToPlane": false,
          "willing": "not_applicable",
          "objectEligibility": {
            "wornOrCarried": "not_applicable",
            "magicalStatus": "not_applicable",
            "fixedToSurface": "not_applicable",
            "maxSize": "not_applicable",
            "maxWeightPounds": "not_applicable",
            "maxWeightScaling": "not_applicable"
          },
          "communicationPrerequisites": {
            "canHearCaster": "not_applicable",
            "canUnderstandCaster": "not_applicable",
            "canSeeCaster": "not_applicable"
          },
          "abilityThreshold": {
            "ability": "not_applicable",
            "operator": "not_applicable",
            "value": "not_applicable"
          },
          "selfRelation": "not_applicable"
        },
        "requiresStatus": [],
        "saveModifiers": [],
        "saveOutcomeOverrides": []
      },
      "utilityType": "sensory",
      "description": "Flame-like shadows make the caster Heavily Obscured to others and change light within 10 feet: Dim Light becomes Darkness, and Bright Light becomes Dim Light.",
      "scaling": {
        "type": "slot_level",
        "bonusPerLevel": "",
        "customFormula": ""
      },
      "grantedActions": [],
      "attackAugments": [],
      "controlOptions": [],
      "taunt": {
        "disadvantageAgainstOthers": false,
        "leashRangeFeet": 0,
        "breakConditions": []
      },
      "savePenalty": {
        "dice": "",
        "flat": 0,
        "applies": "next_save",
        "duration": {
          "type": "rounds",
          "value": 0
        }
      },
      "light": {
        "brightRadius": 0,
        "dimRadius": 0,
        "attachedTo": "caster",
        "color": "",
        "colorChoice": "not_applicable",
        "opaqueCoverBlocks": "not_applicable",
        "emitsHeat": "not_applicable",
        "ignitesObjects": "not_applicable",
        "consumesFuel": "not_applicable",
        "canBeCoveredOrHidden": "not_applicable",
        "canBeSmotheredOrQuenched": "not_applicable"
      },
      "conditionalEndings": []
    }
  ],
  "arbitrationType": "mechanical",
  "aiContext": {
    "prompt": "",
    "playerInputRequired": false
  },
  "description": "Flame-like shadows wreathe your body until the spell ends, causing you to become heavily obscured to others. The shadows turn dim light within 10 feet of you into darkness, and bright light in the same area to dim light. Until the spell ends, you have resistance to radiant damage. In addition, whenever a creature within 10 feet of you hits you with an attack, the shadows lash out at that creature, dealing it 2d8 necrotic damage.",
  "higherLevels": "",
  "tags": []
}
